<?xml version="1.0" encoding="utf-8" ?>
<dwsync>
<file name="chombas-01.png" server="ftp.gylenterprise.com.ar" local="129856716000000000" remote="129856716000000000" />
<file name="chombas.html" server="ftp.gylenterprise.com.ar" local="130202038538389713" remote="130202146200000000" />
<file name="chombas2.html" server="ftp.gylenterprise.com.ar" local="129856716000000000" remote="129856716000000000" />
<file name="chombas2b.html" server="ftp.gylenterprise.com.ar" local="129883500000000000" remote="129883500000000000" />
<file name="chombas3.html" server="ftp.gylenterprise.com.ar" local="129856716000000000" remote="129856716000000000" />
<file name="chombas3b.html" server="ftp.gylenterprise.com.ar" local="129896138400000000" remote="129896138400000000" />
<file name="chombasb.html" server="ftp.gylenterprise.com.ar" local="129896148600000000" remote="129896148600000000" />
<file name="chombasc.css" server="ftp.gylenterprise.com.ar" local="129896148600000000" remote="129896148600000000" />
<file name="chombasc.html" server="ftp.gylenterprise.com.ar" local="129896149200000000" remote="129896149200000000" />
<file name="contactengine.php" server="ftp.gylenterprise.com.ar" local="129856716000000000" remote="129856716000000000" />
<file name="contactenginechombas2.php" server="ftp.gylenterprise.com.ar" local="129856716000000000" remote="129856716000000000" />
<file name="contactenginechombas2b.php" server="ftp.gylenterprise.com.ar" local="129856716000000000" remote="129856716000000000" />
<file name="contactenginechombas3.php" server="ftp.gylenterprise.com.ar" local="129856716000000000" remote="129856716000000000" />
<file name="contactenginechombas3b.php" server="ftp.gylenterprise.com.ar" local="129856716000000000" remote="129856716000000000" />
<file name="contactenginechombasb.php" server="ftp.gylenterprise.com.ar" local="129856716000000000" remote="129856716000000000" />
<file name="contactenginechombasc.php" server="ftp.gylenterprise.com.ar" local="129896148600000000" remote="129896148600000000" />
<file name="contactthanks.html" server="ftp.gylenterprise.com.ar" local="129856716000000000" remote="129856716000000000" />
<file name="contactthanks.php" server="ftp.gylenterprise.com.ar" local="129856716000000000" remote="129856716000000000" />
<file name="contactthanks2.html" server="ftp.gylenterprise.com.ar" local="129856716000000000" remote="129856716000000000" />
<file name="contactthankschombas2.html" server="ftp.gylenterprise.com.ar" local="129954796200000000" remote="129954796200000000" />
<file name="contactthankschombas2b.html" server="ftp.gylenterprise.com.ar" local="129856716000000000" remote="129856716000000000" />
<file name="contactthankschombas3.html" server="ftp.gylenterprise.com.ar" local="129856716000000000" remote="129856716000000000" />
<file name="contactthankschombas3b.html" server="ftp.gylenterprise.com.ar" local="129856716000000000" remote="129856716000000000" />
<file name="contactthankschombasb.html" server="ftp.gylenterprise.com.ar" local="129856716000000000" remote="129856716000000000" />
<file name="contactthankschombasc.html" server="ftp.gylenterprise.com.ar" local="129896148000000000" remote="129896148000000000" />
<file name="style.css" server="ftp.gylenterprise.com.ar" local="129856716000000000" remote="129856716000000000" />
<file name="style2.css" server="ftp.gylenterprise.com.ar" local="129856716000000000" remote="129856716000000000" />
<file name="style3.css" server="ftp.gylenterprise.com.ar" local="129856716000000000" remote="129856716000000000" />
</dwsync>